tdxtimecheck/__init__.py
tdxtimecheck/cli.py
tdxtimecheck-1.0.3.dist-info/METADATA
tdxtimecheck-1.0.3.dist-info/WHEEL
tdxtimecheck-1.0.3.dist-info/entry_points.txt
tdxtimecheck-1.0.3.dist-info/top_level.txt
tdxtimecheck-1.0.3.dist-info/RECORD
