Metadata-Version: 2.1
Name: tdxtimecheck
Version: 1.0.3
Summary: A CLI tool to calculate worked vs target hours
Author-email: Vigil Thomas <vigilthomas17@gmail.com>
License: MIT
Requires-Python: >=3.7
